{
  "id": "metallic",
  "index": 33,

  "name": "Металлик",
  "description": "Существует ошибочное мнение, что данной расцветкой пользуются в условиях дефицита лакокрасочных материалов. На самом деле — это специальное покрытие, особым образом отражающее свет. Бликовый шум, создаваемый таким покрытием, вносит помехи в работу некоторых систем наведения.",

  "baseItemId": 246572,
  "previewResourceId": 246572,

  "rank": 6,
  "price": 2100,

  "coloring": 542023,

  "properties": [
    { "property": "THUNDER_RESISTANCE", "value": 20 }
  ]
}
